etf_scraper/__init__.py
etf_scraper/api.py
etf_scraper/base.py
etf_scraper/config.py
etf_scraper/main.py
etf_scraper/scrapers.py
etf_scraper/storage.py
etf_scraper/utils.py
etf_scraper/data/listings.csv
etf_scraper-0.1.2.dist-info/LICENSE.txt
etf_scraper-0.1.2.dist-info/METADATA
etf_scraper-0.1.2.dist-info/WHEEL
etf_scraper-0.1.2.dist-info/top_level.txt
etf_scraper-0.1.2.dist-info/RECORD
