Metadata-Version: 2.2
Name: etf_scraper
Version: 0.1.2
Summary: Scrape ETF and Mutual Fund holdings from major providers
Project-URL: Home, https://github.com/nikulpatel3141/ETF-Scraper
Classifier: Programming Language :: Python :: 3
Classifier: License :: OSI Approved :: MIT License
Requires-Python: >=3.8
License-File: LICENSE.txt
Requires-Dist: requests
Requires-Dist: tenacity
Requires-Dist: pandas>=1.5
Requires-Dist: numpy<2.0
Requires-Dist: pandas_market_calendars
Requires-Dist: openpyxl
Provides-Extra: cloud
Requires-Dist: gcsfs; extra == "cloud"
Requires-Dist: fastparquet<=2023.01; extra == "cloud"
Requires-Dist: google-cloud-bigquery; extra == "cloud"
Provides-Extra: tests
Requires-Dist: pytest; extra == "tests"
